setup.py
simple_timer/__init__.py
simple_timer/timer.py
simple_timer_baxxter.egg-info/PKG-INFO
simple_timer_baxxter.egg-info/SOURCES.txt
simple_timer_baxxter.egg-info/dependency_links.txt
simple_timer_baxxter.egg-info/not-zip-safe
simple_timer_baxxter.egg-info/top_level.txt