Metadata-Version: 2.1
Name: simple-timer-baxxter
Version: 1.2
Summary: its a simple timer 
Home-page: 
Author: AMIRBAXXTER
Author-email: amirmasoodpormahdi@gmail.com
License: MIT
